pypto/__init__.py
pypto/_controller.py
pypto/_element.py
pypto/_op_wrapper.py
pypto/_utils.py
pypto/config.py
pypto/converter.py
pypto/cost_model.py
pypto/enum.py
pypto/experimental.py
pypto/operation.py
pypto/operator.py
pypto/pass_config.py
pypto/pypto_impl.cpython-311-aarch64-linux-gnu.so
pypto/pypto_impl.pyi
pypto/runtime.py
pypto/symbolic_scalar.py
pypto/tensor.py
pypto/lib/libc_sec.so
pypto/lib/libpypto_ctrl_server.a
pypto/lib/libtile_fwk_codegen.so
pypto/lib/libtile_fwk_compiler.so
pypto/lib/libtile_fwk_interface.so
pypto/lib/libtile_fwk_runtime.so
pypto/lib/libtile_fwk_runtime_stub.so
pypto/lib/libtile_fwk_simulation.so
pypto/lib/libtile_fwk_simulation_ca.so
pypto/lib/libtile_fwk_simulation_platform.so
pypto/lib/libtilefwk_backend_server.so
pypto/lib/configs/A2A3.ini
pypto/lib/configs/tile_fwk_config.json
pypto/lib/configs/tile_fwk_config_ng.json
pypto/lib/configs/tile_fwk_config_schema.json
pypto/lib/configs/tile_fwk_types.json
pypto/lib/include/mock/mock_helper.h
pypto/lib/include/mock/mock_inst.h
pypto/lib/include/mock/mock_types.h
pypto/lib/include/tilefwk/aicore_data.h
pypto/lib/include/tilefwk/aicore_print.h
pypto/lib/include/tilefwk/aicore_runtime.h
pypto/lib/include/tilefwk/aicpu_common.h
pypto/lib/include/tilefwk/aicpu_distributed.h
pypto/lib/include/tilefwk/aicpu_runtime.h
pypto/lib/include/tilefwk/core_func_data.h
pypto/lib/include/tileop/TileOpImpl.h
pypto/lib/include/tileop/tileop_common.h
pypto/lib/include/tileop/a2a3/cube.h
pypto/lib/include/tileop/a2a3/fixpipe.h
pypto/lib/include/tileop/a2a3/mte.h
pypto/lib/include/tileop/a2a3/vector.h
pypto/lib/include/tileop/a2a3/vector_bin.h
pypto/lib/include/tileop/a2a3/vector_bin_brc.h
pypto/lib/include/tileop/a2a3/vector_una.h
pypto/lib/include/tileop/a2a3/dynamic/aicpu_call.h
pypto/lib/include/tileop/a2a3/dynamic/cube_dyn.h
pypto/lib/include/tileop/a2a3/dynamic/mte_dyn.h
pypto/lib/include/tileop/a2a3/dynamic/vector_bin_brc_dyn.h
pypto/lib/include/tileop/a2a3/dynamic/vector_bin_dyn.h
pypto-0.1.0.dist-info/licenses/LICENSE
pypto-0.1.0.dist-info/METADATA
pypto-0.1.0.dist-info/WHEEL
pypto-0.1.0.dist-info/top_level.txt
pypto-0.1.0.dist-info/RECORD
