Metadata-Version: 2.4
Name: pypto
Version: 0.1.0
Summary: A high-performance programming framework for tile-centric computing
Author-email: PyPTO Team <pto@cann.osinfra.cn>
License-Expression: LicenseRef-CANN-Open-Software-License-Agreement-Version-2.0
Project-URL: Homepage, https://gitcode.com/cann/pypto
Project-URL: Repository, https://gitcode.com/cann/pypto
Project-URL: Bug Tracker, https://gitcode.com/cann/pypto/issues
Keywords: python,pto,tile,tile-centric
Classifier: Development Status :: 4 - Beta
Classifier: Intended Audience :: Developers
Classifier: Topic :: Software Development :: Compilers
Classifier: Programming Language :: Python :: 3
Classifier: Programming Language :: Python :: 3.9
Classifier: Programming Language :: Python :: 3.10
Classifier: Programming Language :: Python :: 3.11
Classifier: Programming Language :: Python :: 3.12
Requires-Python: >=3.9
License-File: LICENSE
Provides-Extra: dev
Requires-Dist: setuptools>=77.0.3; extra == "dev"
Requires-Dist: pybind11>=2.13.6; extra == "dev"
Requires-Dist: pip; extra == "dev"
Requires-Dist: build; extra == "dev"
Requires-Dist: packaging; extra == "dev"
Requires-Dist: pytest; extra == "dev"
Requires-Dist: pytest-forked; extra == "dev"
Requires-Dist: pytest-xdist; extra == "dev"
Provides-Extra: tests
Requires-Dist: pytest; extra == "tests"
Requires-Dist: pytest-forked; extra == "tests"
Requires-Dist: pytest-xdist; extra == "tests"
Dynamic: license-file
